CHANGES.txt
LICENCE.txt
MANIFEST.in
README.rst
setup.py
django_503/__init__.py
django_503/admin.py
django_503/maintenance.py
django_503/middleware.py
django_503/models.py
django_503/views.py
django_503.egg-info/PKG-INFO
django_503.egg-info/SOURCES.txt
django_503.egg-info/dependency_links.txt
django_503.egg-info/requires.txt
django_503.egg-info/top_level.txt
tests/__init__.py
tests/models.py
tests/tests.py
tests/urls.py
tests/views.py