Metadata-Version: 1.0
Name: django-503
Version: 0.1
Summary: An app to show 503 error page, while your django site is on maintenance.
Home-page: https://github.com/coagulant/django-503
Author: Ilya Baryshev
Author-email: baryshev@gmail.com
License: MIT
Platform: UNKNOWN
Classifier: Development Status :: 3 - Alpha
Classifier: Framework :: Django
Classifier: Intended Audience :: Developers
Classifier: License :: OSI Approved :: MIT License
Classifier: Operating System :: OS Independent
Classifier: Programming Language :: Python
